LICENSE
README.md
setup.py
grama/__init__.py
grama/comp_building.py
grama/comp_metamodels.py
grama/core.py
grama/dataframe.py
grama/eval_contour.py
grama/eval_defaults.py
grama/eval_opt.py
grama/eval_pnd.py
grama/eval_random.py
grama/eval_tail.py
grama/fit_synonyms.py
grama/marginals.py
grama/mutate_helpers.py
grama/plot_auto.py
grama/spc.py
grama/string_helpers.py
grama/support.py
grama/tools.py
grama/tran_is.py
grama/tran_pivot.py
grama/tran_shapley.py
grama/tran_summaries.py
grama/tran_tools.py
grama/data/__init__.py
grama/data/datasets.py
grama/data/diamonds.csv
grama/data/psaap.csv
grama/data/ruff.csv
grama/data/shewhart1931-table3.csv
grama/data/stang.csv
grama/data/stang_long.csv
grama/data/trajectory_full.csv
grama/data/trajectory_windowed.csv
grama/dfply/__init__.py
grama/dfply/base.py
grama/dfply/count.py
grama/dfply/group.py
grama/dfply/join.py
grama/dfply/mask_helpers.py
grama/dfply/reshape.py
grama/dfply/select.py
grama/dfply/set_ops.py
grama/dfply/string_helpers.py
grama/dfply/subset.py
grama/dfply/summarize.py
grama/dfply/summary_functions.py
grama/dfply/transform.py
grama/dfply/vector.py
grama/dfply/window_functions.py
grama/eval/__init__.py
grama/eval/eval_pyDOE.py
grama/fit/__init__.py
grama/fit/fit_lolo.py
grama/fit/fit_scikitlearn.py
grama/fit/fit_statsmodels.py
grama/models/__init__.py
grama/models/cantilever_beam.py
grama/models/channel1d.py
grama/models/circuit_RLC.py
grama/models/ishigami.py
grama/models/linear_normal.py
grama/models/pareto_random.py
grama/models/pipe_flow.py
grama/models/piston.py
grama/models/plane_laminate.py
grama/models/plate_buckling.py
grama/models/poly.py
grama/models/sir.py
grama/models/test.py
grama/models/trajectory_linear_drag.py
grama/psdr/__init__.py
grama/psdr/basis.py
grama/psdr/exceptions.py
grama/psdr/function.py
grama/psdr/gn.py
grama/psdr/initialization.py
grama/psdr/local_linear.py
grama/psdr/misc.py
grama/psdr/pgf.py
grama/psdr/poly.py
grama/psdr/polyridge.py
grama/psdr/psdr_tools.py
py_grama.egg-info/PKG-INFO
py_grama.egg-info/SOURCES.txt
py_grama.egg-info/dependency_links.txt
py_grama.egg-info/requires.txt
py_grama.egg-info/top_level.txt
