Metadata-Version: 2.1
Name: py_grama
Version: 0.3.8
Summary: A grammar of model analysis
Home-page: https://github.com/zdelrosario/py_grama
Author: Zachary del Rosario
Author-email: zdelrosario@outlook.com
License: MIT
Classifier: Programming Language :: Python :: 3
Classifier: License :: OSI Approved :: MIT License
Classifier: Operating System :: OS Independent
Requires-Python: >=3.8, <3.10
License-File: LICENSE
Requires-Dist: matplotlib
Requires-Dist: numpy<2.0,>=1.15
Requires-Dist: scipy>=1.10
Requires-Dist: pandas<=1.5.3
Requires-Dist: plotnine>=0.8.0
Requires-Dist: scipy
Requires-Dist: toolz
Requires-Dist: networkx
Provides-Extra: matminer
Requires-Dist: pymatgen==2021.2.8.1; extra == "matminer"
Requires-Dist: matminer; extra == "matminer"
Provides-Extra: sklearn
Requires-Dist: scikit-learn; extra == "sklearn"
Provides-Extra: statsmodels
Requires-Dist: statsmodels; extra == "statsmodels"
Provides-Extra: pydoe
Requires-Dist: pyDOE; extra == "pydoe"
Provides-Extra: umap
Requires-Dist: umap-learn; extra == "umap"
Provides-Extra: dev
Requires-Dist: pymatgen==2021.2.8.1; extra == "dev"
Requires-Dist: matminer; extra == "dev"
Requires-Dist: scikit-learn; extra == "dev"
Requires-Dist: statsmodels; extra == "dev"
Requires-Dist: pyDOE; extra == "dev"
Requires-Dist: umap-learn; extra == "dev"
